graphPlot/__init__.py
graphPlot/graphPlot.py
graphPlot-1.0.0.dist-info/LICENSE
graphPlot-1.0.0.dist-info/METADATA
graphPlot-1.0.0.dist-info/WHEEL
graphPlot-1.0.0.dist-info/top_level.txt
graphPlot-1.0.0.dist-info/RECORD
