Metadata-Version: 2.1
Name: graphPlot
Version: 1.0.0
Summary: Plot (di)graphs using a timestep simulation of charged particles and springs
Home-page: https://github.com/francisp336/graphPlot
Author: Peter E. Francis
Author-email: francisp336@gmail.com
Keywords: Graph
Requires-Python: >=3.0.0
License-File: LICENSE
Requires-Dist: matplotlib
Requires-Dist: numpy
